MANIFEST.in
README.md
setup.py
xmind2Excel/__init__.py
xmind2Excel/__init__.pyc
xmind2Excel/__version__.py
xmind2Excel/favicon.ico
xmind2Excel/favicon.png
xmind2Excel/main.py
xmind2Excel/test.py
xmind2Excel/timg.jpg
xmind2Excel/ui3.py
xmind2Excel.egg-info/PKG-INFO
xmind2Excel.egg-info/SOURCES.txt
xmind2Excel.egg-info/dependency_links.txt
xmind2Excel.egg-info/requires.txt
xmind2Excel.egg-info/top_level.txt
xmind2Excel.egg-info/zip-safe
xmind2Excel/__pycache__/__init__.cpython-37.pyc
xmind2Excel/__pycache__/__version__.cpython-37.pyc
xmind2Excel/__pycache__/main.cpython-37.pyc
xmind2Excel/__pycache__/ui3.cpython-37.pyc
xmind2Excel/file/xmind-sdk-python-master/.gitignore
xmind2Excel/file/xmind-sdk-python-master/LICENSE.md
xmind2Excel/file/xmind-sdk-python-master/README.md
xmind2Excel/file/xmind-sdk-python-master/example.py
xmind2Excel/file/xmind-sdk-python-master/example2.py
xmind2Excel/file/xmind-sdk-python-master/logo.jpeg
xmind2Excel/file/xmind-sdk-python-master/mac.xmind
xmind2Excel/file/xmind-sdk-python-master/setup.py
xmind2Excel/file/xmind-sdk-python-master/test2.xmind
xmind2Excel/file/xmind-sdk-python-master/build/lib/xmind/__init__.py
xmind2Excel/file/xmind-sdk-python-master/build/lib/xmind/utils.py
xmind2Excel/file/xmind-sdk-python-master/build/lib/xmind/core/__init__.py
xmind2Excel/file/xmind-sdk-python-master/build/lib/xmind/core/const.py
xmind2Excel/file/xmind-sdk-python-master/build/lib/xmind/core/loader.py
xmind2Excel/file/xmind-sdk-python-master/build/lib/xmind/core/markerref.py
xmind2Excel/file/xmind-sdk-python-master/build/lib/xmind/core/mixin.py
xmind2Excel/file/xmind-sdk-python-master/build/lib/xmind/core/notes.py
xmind2Excel/file/xmind-sdk-python-master/build/lib/xmind/core/position.py
xmind2Excel/file/xmind-sdk-python-master/build/lib/xmind/core/relationship.py
xmind2Excel/file/xmind-sdk-python-master/build/lib/xmind/core/saver.py
xmind2Excel/file/xmind-sdk-python-master/build/lib/xmind/core/sheet.py
xmind2Excel/file/xmind-sdk-python-master/build/lib/xmind/core/title.py
xmind2Excel/file/xmind-sdk-python-master/build/lib/xmind/core/topic.py
xmind2Excel/file/xmind-sdk-python-master/build/lib/xmind/core/workbook.py
xmind2Excel/file/xmind-sdk-python-master/xmind.egg-info/PKG-INFO
xmind2Excel/file/xmind-sdk-python-master/xmind.egg-info/SOURCES.txt
xmind2Excel/file/xmind-sdk-python-master/xmind.egg-info/dependency_links.txt
xmind2Excel/file/xmind-sdk-python-master/xmind.egg-info/requires.txt
xmind2Excel/file/xmind-sdk-python-master/xmind.egg-info/top_level.txt
