Metadata-Version: 2.1
Name: xmind2Excel
Version: 0.4.0
Summary: xmind2Excel is a tool, change the xmind to excel.
Home-page: https://pypi.org/project/xxmind/#description
Author: goblinintree
Author-email: goblinintree@126.com
License: MIT
Keywords: xlsx,excel,xmind2Excel
Platform: all
Classifier: Environment :: Web Environment
Classifier: License :: OSI Approved :: MIT License
Classifier: Operating System :: Microsoft
Classifier: Programming Language :: Python :: 3.7
